{
  "id": "supports.four_legs_rectangular.v1",
  "name": "Four rectangular legs at corners",
  "category": "support",
  "features": ["four_legs", "rectangular_legs", "corner_placed"],
  "parameters": {
    "leg_width_mm": {"default": 40, "min": 20, "max": 80},
    "leg_depth_mm": {"default": 40, "min": 20, "max": 80},
    "height_mm": {"default": 720, "min": 400, "max": 760},
    "inset_mm": {"default": 20, "min": 5, "max": 50}
  },
  "cad_rules": {"top_view": "RECTANGLE_HIDDEN", "layer": "HIDDEN", "front_elevation": "RECTANGLE"}
}
